MANIFEST.in
setup.py
docs/HISTORY.txt
src/dolmen/__init__.py
src/dolmen.storage.egg-info/PKG-INFO
src/dolmen.storage.egg-info/SOURCES.txt
src/dolmen.storage.egg-info/dependency_links.txt
src/dolmen.storage.egg-info/namespace_packages.txt
src/dolmen.storage.egg-info/not-zip-safe
src/dolmen.storage.egg-info/requires.txt
src/dolmen.storage.egg-info/top_level.txt
src/dolmen/storage/README.txt
src/dolmen/storage/__init__.py
src/dolmen/storage/annotations.py
src/dolmen/storage/container.py
src/dolmen/storage/interfaces.py
src/dolmen/storage/tests/__init__.py
src/dolmen/storage/tests/ftesting.zcml
src/dolmen/storage/tests/test_all.py
src/dolmen/storage/tests/annotations/__init__.py
src/dolmen/storage/tests/annotations/property.py
src/dolmen/storage/tests/annotations/storage.py
src/dolmen/storage/tests/container/__init__.py
src/dolmen/storage/tests/container/btree.py
src/dolmen/storage/tests/container/delegate.py